{"meta":{"district":"BANGALORE URBAN","ac_num":90,"ac_name":"AC-90","part_num":261,"voter_count":153},"voters":[{"sn":1,"vn":"Muragesh","vk":"ಮುರಗೇಶ್‌","rn":"Subbaherivar","rk":"ಸುಬ್ಬಹೆರಿವರ್‌","rt":"F","g":"M","a":68,"hn":"182","id":null,"pn":261,"dq":1},{"sn":2,"vn":"0 Tadd 308 Periyanna No 38","vk":"£0 & Tadd 308 ಪೆರಿಯಣ್ಣ no 38","rn":"","rk":"","rt":"","g":"M","a":null,"hn":"183","id":null,"pn":261,"dq":0},{"sn":3,"vn":"Narasimhalu 308 Pemcalayya No 33","vk":"ನರಸಿಂಹಲು 308 ಪೆಂಚಲಯ್ಯ no 33","rn":"","rk":"","rt":"","g":"M","a":null,"hn":"184","id":null,"pn":261,"dq":0},{"sn":4,"vn":"Ramacamdrappa 308 Vemkatiramanappa No 38","vk":"ರಾಮಚಂದ್ರಪ್ಪ 308 ವೆಂಕಟಿರಮಣಪ್ಪ no 38","rn":"","rk":"","rt":"","g":"M","a":null,"hn":"185","id":null,"pn":261,"dq":0},{"sn":5,"vn":"Keshava","vk":"ಕೇಶವ","rn":"Cinnaraj","rk":"ಚಿನ್ನರಾಜ್‌","rt":"F","g":"M","a":38,"hn":"186","id":null,"pn":261,"dq":1},{"sn":6,"vn":"Seenappa 308 Cikkamuniyappa No 43","vk":"ಸೀನಪ್ಪ 308 ಚಿಕ್ಕಮುನಿಯಪ್ಪ no 43","rn":"","rk":"","rt":"","g":"M","a":null,"hn":"190","id":null,"pn":261,"dq":0},{"sn":7,"vn":"Bairappa","vk":"ಬೈರಪ್ಪ","rn":"Caudappa","rk":"ಚೌಡಪ್ಪ","rt":"F","g":"M","a":51,"hn":"191","id":null,"pn":261,"dq":1},{"sn":8,"vn":"Selvakumar","vk":"ಸೆಲ್ವಕುಮಾರ್‌","rn":"Subramani","rk":"ಸುಬ್ರಮಣಿ","rt":"F","g":"M","a":31,"hn":"193","id":null,"pn":261,"dq":1},{"sn":9,"vn":"Baiyanna","vk":"ಬೈಯಣ್ಣ","rn":"Sonnappa","rk":"ಸೊಣ್ಣಪ್ಪ","rt":"F","g":"M","a":63,"hn":"194","id":null,"pn":261,"dq":1},{"sn":10,"vn":"Ar Je Tannar 308 Jalal Tavar Gam 53","vk":"ಆರ್‌ ಜೆ ತಣ್ಣರ್‌ 308 ಜಾಲಾಲ್‌ ತವರ್‌ ಗಂ 53","rn":"","rk":"","rt":"","g":"M","a":53,"hn":"196","id":null,"pn":261,"dq":0},{"sn":11,"vn":"Es Raju","vk":"ಏಸ್‌ ರಾಜು","rn":"Shreenivas","rk":"ಶ್ರೀನಿವಾಸ್‌","rt":"F","g":"M","a":42,"hn":"197","id":null,"pn":261,"dq":1},{"sn":12,"vn":"Vijayakumar 308 Muddappa No 46","vk":"ವಿಜಯಕುಮಾರ್‌ 308 ಮುದ್ದಪ್ಪ no 46","rn":"","rk":"","rt":"","g":"M","a":null,"hn":"198","id":null,"pn":261,"dq":0},{"sn":13,"vn":"Eai Muniraju","vk":"ಏಐ ಮುನಿರಾಜು","rn":"Apayan Na","rk":"ಅಪಯಣ್‌ಣ","rt":"F","g":"M","a":48,"hn":"199","id":null,"pn":261,"dq":1},{"sn":14,"vn":"Gurusiddappa","vk":"ಗುರುಸಿದ್ದಪ್ಪ","rn":"Basappa","rk":"ಬಸಪ್ಪ","rt":"F","g":"M","a":36,"hn":"202","id":null,"pn":261,"dq":1},{"sn":15,"vn":"Dumacar","vk":"ದೂಮಾಚಾರ್‌","rn":"Hanumamtacar","rk":", ಹನುಮಂತಚಾರ್‌","rt":"F","g":"M","a":78,"hn":"203","id":null,"pn":261,"dq":1},{"sn":16,"vn":"Munisthamappa","vk":"ಮುನಿಸ್ಥಾಮಪ್ಪ","rn":"Doddappanna","rk":"ದೊಡ್ಡಪ್ಪಣ್ಣ","rt":"F","g":"M","a":63,"hn":"204","id":null,"pn":261,"dq":1},{"sn":17,"vn":"A Gamgadhara No","vk":"ಅ ಗಂಗಾಧರ NO","rn":"Munisvamappa","rk":"ಮುನಿಸ್ವಾಮಪ್ಪ","rt":"F","g":"M","a":39,"hn":"204","id":null,"pn":261,"dq":1},{"sn":18,"vn":"A Ar Sampattukumar 308 Jisiraj Manikkam Gam 44","vk":"ಆ ಆರ್‌ ಸಂಪತ್ತುಕುಮಾರ್‌ 308 ಜಿಸಿರಾಜ್‌ ಮಾಣಿಕ್ಕಂ ಗಂ 44","rn":"","rk":"","rt":"","g":"M","a":44,"hn":"204","id":null,"pn":261,"dq":0},{"sn":19,"vn":"Vemkatamma","vk":"ವೆಂಕಟಮ್ಮ","rn":"Lakshmayya","rk":"ಲಕ್ಷ್ಮಯ್ಯ","rt":"H","g":"F","a":48,"hn":"205","id":null,"pn":261,"dq":1},{"sn":20,"vn":"Bi En Krishnappa","vk":"ಬಿ ಏನ್‌ ಕೃಷ್ಣಪ್ಪ","rn":"Namjumdappa","rk":"ನಂಜುಂಡಪ್ಪ","rt":"F","g":"M","a":58,"hn":"206","id":null,"pn":261,"dq":1},{"sn":21,"vn":"Em Muniyappa","vk":"ಏಂ ಮುನಿಯಪ್ಪ","rn":"Motappa","rk":"ಮೋಟಪ್ಪ","rt":"F","g":"M","a":63,"hn":"207","id":null,"pn":261,"dq":1},{"sn":22,"vn":"Es Nagaraj","vk":"ಏಸ್‌ ನಾಗರಾಜ್‌","rn":"Sonnappa","rk":"ಸೊಣ್ಣಪ್ಪ","rt":"F","g":"M","a":48,"hn":"208","id":null,"pn":261,"dq":1},{"sn":23,"vn":"Amjanappa 308 Narasimhappa No 45","vk":"ಅಂಜನಪ್ಪ 308 ನರಸಿಂಹಪ್ಪ no 45","rn":"","rk":"","rt":"","g":"M","a":null,"hn":"209","id":null,"pn":261,"dq":0},{"sn":24,"vn":"Govimdaraj 308 Narasimhappa Gam 38","vk":"ಗೋವಿಂದರಾಜ್‌ 308 ನರಸಿಂಹಪ್ಪ ಗಂ 38","rn":"","rk":"","rt":"","g":"M","a":38,"hn":"210","id":null,"pn":261,"dq":0},{"sn":25,"vn":"Narayanappa","vk":"ನಾರಾಯಣಪ್ಪ","rn":"Mautappa","rk":"ಮೌಟಪ್ಪ","rt":"F","g":"M","a":48,"hn":"211","id":null,"pn":261,"dq":1},{"sn":26,"vn":"Appayyanna","vk":"ಅಪ್ಪಯ್ಯಣ್ಣ","rn":"Namjumdappa","rk":"ನಂಜುಂಡಪ್ಪ","rt":"F","g":"M","a":63,"hn":"212","id":null,"pn":261,"dq":1},{"sn":27,"vn":"0 Ramayya","vk":"2) 0 ರಾಮಯ್ಯ","rn":"Munisvamappa","rk":"ಮುನಿಸ್ವಾಮಪ್ಪ","rt":"F","g":"M","a":63,"hn":"213","id":null,"pn":261,"dq":1},{"sn":28,"vn":"Krishnamma","vk":"ಕೃಷ್ಣಮ್ಮ","rn":"Muddhappa","rk":"ಮುದ್ಧಪ್ಪ","rt":"H","g":"F","a":73,"hn":"214","id":null,"pn":261,"dq":1},{"sn":29,"vn":"Iri","vk":"7ಿರಿ","rn":"Gujappa","rk":"ಗುಜಪ್ಪ","rt":"F","g":"M","a":34,"hn":"215","id":null,"pn":261,"dq":1},{"sn":30,"vn":"Muniyappa","vk":"ಮುನಿಯಪ್ಪ","rn":"Vemkatasvamappa","rk":".. ವೆಂಕಟಸ್ವಾಮಪ್ಪ","rt":"F","g":"M","a":58,"hn":"216","id":null,"pn":261,"dq":1},{"sn":31,"vn":"Basappa 308 Sennegauda Gam 48","vk":"ಬಸಪ್ಪ 308 ಸೆನ್ನೆಗೌಡ ಗಂ 48","rn":"","rk":"","rt":"","g":"M","a":48,"hn":"217","id":null,"pn":261,"dq":0},{"sn":32,"vn":"Gulhappa","vk":"ಗುಳ್ಹಪ್ಪ","rn":"Hanumamtappa","rk":"ಹನುಮಂತಪ್ಪ","rt":"F","g":"M","a":63,"hn":"218","id":null,"pn":261,"dq":1},{"sn":33,"vn":"Hv Ramayya","vk":"2) HV ರಾಮಯ್ಯ","rn":"Namjumdappa","rk":"ನಂಜುಂಡಪ್ಪ","rt":"F","g":"M","a":64,"hn":"222","id":null,"pn":261,"dq":1},{"sn":34,"vn":"Muniraju","vk":"ಮುನಿರಾಜು","rn":"Muniyappa","rk":"ಮುನಿಯಪ್ಪ","rt":"F","g":"M","a":38,"hn":"223","id":null,"pn":261,"dq":1},{"sn":35,"vn":"Kamta","vk":"ಕಾಂತ","rn":"Nagaraju","rk":"ನಾಗರಾಜು","rt":"H","g":"F","a":49,"hn":"224","id":null,"pn":261,"dq":1},{"sn":36,"vn":"Suresh Nayak","vk":"ಸುರೇಶ್‌ ನಾಯಕ್‌","rn":"Ramajeenayak","rk":"ರಾಮಜೀನಾಯಕ್‌","rt":"F","g":"M","a":40,"hn":"225","id":null,"pn":261,"dq":1},{"sn":37,"vn":"Bi Em Krishnappa","vk":"ಬಿ ಏಂ ಕೃಷ್ಣಪ್ಪ","rn":"Muvisthamappa","rk":"ಮುವಿಸ್ಥಾಮಪ್ಪ","rt":"F","g":"M","a":63,"hn":"226","id":null,"pn":261,"dq":1},{"sn":38,"vn":"Gumdappa","vk":"ಗುಂಡಪ್ಪ","rn":"Cokkappa","rk":"ಚೊಕ್ಕಪ್ಪ","rt":"F","g":"M","a":71,"hn":"227","id":null,"pn":261,"dq":1},{"sn":39,"vn":"Vemkatesh 308 Gumdappa No 35","vk":"ವೆಂಕಟೇಶ್‌ 308 ಗುಂಡಪ್ಪ no 35","rn":"","rk":"","rt":"","g":"M","a":null,"hn":"228","id":null,"pn":261,"dq":0},{"sn":40,"vn":"Ramakrishna 308 Narappa Gam 39","vk":"ರಾಮಕೃಷ್ಣ 308 ನಾರಪ್ಪ ಗಂ 39","rn":"","rk":"","rt":"","g":"M","a":39,"hn":"229","id":null,"pn":261,"dq":0},{"sn":41,"vn":"Muniyappa 308 Narasappa No 73","vk":"ಮುನಿಯಪ್ಪ 308 ನರಸಪ್ಪ no 73","rn":"","rk":"","rt":"","g":"M","a":null,"hn":"230","id":null,"pn":261,"dq":0},{"sn":42,"vn":"Munihanumappa","vk":"ಮುನಿಹನುಮಪ್ಪ","rn":"Sadappa","rk":"ಸಾದಪ್ಪ","rt":"F","g":"M","a":93,"hn":"231","id":null,"pn":261,"dq":1},{"sn":43,"vn":"El Bi Krishnappa","vk":"ಏಲ್‌ ಬಿ ಕೃಷ್ಣಪ್ಪ","rn":"Baccappa","rk":"ಬಚ್ಚಪ್ಪ","rt":"F","g":"M","a":53,"hn":"232","id":null,"pn":261,"dq":1},{"sn":44,"vn":"Muninagappa","vk":"ಮುನಿನಾಗಪ್ಪ","rn":"Papayya","rk":"ಪಾಪಯ್ಯ","rt":"F","g":"M","a":55,"hn":"234","id":null,"pn":261,"dq":1},{"sn":45,"vn":"Lakshmama Rya","vk":"ಲಕ್ಷ್ಮಮ ರ್ಯ","rn":"Muniyappa","rk":"ಮುನಿಯಪ್ಪ","rt":"F","g":"M","a":48,"hn":"235","id":null,"pn":261,"dq":1},{"sn":46,"vn":"Rajanna","vk":"ರಾಜಣ್ಣ","rn":"Muniyappa","rk":"ಮುನಿಯಪ್ಪ","rt":"F","g":"M","a":43,"hn":"236","id":null,"pn":261,"dq":1},{"sn":47,"vn":"Jayamma","vk":"ಜಯಮ್ಮ","rn":"Narayanappa","rk":"ನಾರಾಯಣಪ್ಪ","rt":"H","g":"F","a":68,"hn":"237","id":null,"pn":261,"dq":1},{"sn":48,"vn":"Sunnjamma Now Sammpamgappa 30 73","vk":"ಸೂಣ್ಣ್ಜಮ್ಮ now ಸಂಂಪಂಗಪ್ಪ 30 73","rn":"","rk":"","rt":"","g":"M","a":null,"hn":"238","id":null,"pn":261,"dq":0},{"sn":49,"vn":"En Nagaraj","vk":"ಏನ್‌ ನಾಗರಾಜ್‌","rn":"Sarappa","rk":"ಸಾರಪ್ಪ","rt":"F","g":"M","a":45,"hn":"239","id":null,"pn":261,"dq":1},{"sn":50,"vn":"En Ramayya","vk":"ಏನ್‌ ರಾಮಯ್ಯ","rn":"Cikkanarappa","rk":"ಚಿಕ್ಕನಾರಪ್ಪ","rt":"F","g":"M","a":43,"hn":"240","id":null,"pn":261,"dq":1},{"sn":51,"vn":"En Shreenivas","vk":"ಏನ್‌ ಶ್ರೀನಿವಾಸ್‌","rn":"Cikkanarappa","rk":"ಚಿಕ್ಕನಾರಪ್ಪ","rt":"F","g":"M","a":28,"hn":"241","id":null,"pn":261,"dq":1},{"sn":52,"vn":"En Anamd","vk":"ಏನ್‌ ಆನಂದ್‌","rn":"Cikkanarappa","rk":"ಚಿಕ್ಕನಾರಪ್ಪ","rt":"F","g":"M","a":36,"hn":"242","id":null,"pn":261,"dq":1},{"sn":53,"vn":"En Paramesh","vk":"ಏನ್‌ ಪರಮೇಶ್‌","rn":"Cikkanarappa","rk":"ಚಿಕ್ಕನಾರಪ್ಪ","rt":"F","g":"M","a":30,"hn":"243","id":null,"pn":261,"dq":1},{"sn":54,"vn":"Narasimhappa","vk":"ನರಸಿಂಹಪ್ಪ","rn":"Muneeveerappa","rk":"ಮುನೀವೀರಪ್ಪ","rt":"F","g":"M","a":48,"hn":"244","id":null,"pn":261,"dq":1},{"sn":55,"vn":"Cinnamma","vk":"ಚಿನ್ನಮ್ಮ","rn":"Narappa","rk":"ನಾರಪ್ಪ","rt":"H","g":"F","a":83,"hn":"245","id":null,"pn":261,"dq":1},{"sn":56,"vn":"Diramadas 308 Das No 48","vk":"ಡಿರಾಮದಾಸ್‌ 308 ದಾಸ್‌ no 48","rn":"","rk":"","rt":"","g":"M","a":null,"hn":"246","id":null,"pn":261,"dq":0},{"sn":57,"vn":"Ear Rajappa 308 Rudrappa Gam 25","vk":"*ೆಆರ್‌ ರಾಜಪ್ಪ 308 ರುದ್ರಪ್ಪ ಗಂ 25","rn":"","rk":"","rt":"","g":"M","a":25,"hn":"247","id":null,"pn":261,"dq":0},{"sn":58,"vn":"Vemmkatasthamappa","vk":"ವೆಂಂಕಟಸ್ಥಾಮಪ್ಪ","rn":"Sokkappa","rk":"ಸೊಕ್ಕಪ್ಪ","rt":"F","g":"M","a":78,"hn":"249","id":null,"pn":261,"dq":1},{"sn":59,"vn":"bin","vk":"ಬಿನ್‌","rn":"Narayanappa","rk":"ನಾರಾಯಣಪ್ಪ","rt":"F","g":"M","a":78,"hn":"250","id":null,"pn":261,"dq":1},{"sn":60,"vn":"Yt Oo 308 Krishnappa No 33","vk":"YT Oo 308 ಕೃಷ್ಣಪ್ಪ no 33","rn":"","rk":"","rt":"","g":"M","a":null,"hn":"251","id":null,"pn":261,"dq":0},{"sn":61,"vn":"Yarisampamgappa","vk":"ಯರಿಸಂಪಂಗಪ್ಪ","rn":"Muvisthtamayya","rk":"ಮುವಿಸ್ಥ್ಟಾಮಯ್ಯ","rt":"F","g":"M","a":63,"hn":"252","id":null,"pn":261,"dq":1},{"sn":62,"vn":"Gopi","vk":"ಗೋಪಿ","rn":"Raman","rk":"ರಾಮನ್‌","rt":"F","g":"M","a":28,"hn":"253","id":null,"pn":261,"dq":1},{"sn":63,"vn":"Nataraj","vk":"ನಟರಾಜ್‌","rn":"Nallannonar","rk":"ನಲ್ಲನ್ನೊಣರ್‌","rt":"F","g":"M","a":35,"hn":"254","id":null,"pn":261,"dq":1},{"sn":64,"vn":"Yan Pullayya","vk":"ಯನ್‌ ಪುಲ್ಲಯ್ಯ","rn":"Obayya","rk":"ಒಬಯ್ಯ","rt":"F","g":"M","a":43,"hn":"255","id":null,"pn":261,"dq":1},{"sn":65,"vn":"Hareesh Kumar","vk":"ಹರೀಶ್‌ ಕುಮಾರ್‌","rn":"Sipullayya","rk":"ಸಿಪುಲ್ಲಯ್ಯ","rt":"F","g":"M","a":27,"hn":"256","id":null,"pn":261,"dq":1},{"sn":66,"vn":"Ravi","vk":"ರವಿ","rn":"Durvan","rk":"ದುರ್ವನ್‌","rt":"F","g":"M","a":30,"hn":"257","id":null,"pn":261,"dq":1},{"sn":67,"vn":"Peramal","vk":"ಪೆರಮಾಳ್‌","rn":"Nagappa","rk":"ನಾಗಪ್ಪ","rt":"F","g":"M","a":48,"hn":"258","id":null,"pn":261,"dq":1},{"sn":68,"vn":"Shanmugam","vk":"ಶಣ್ಮುಗಂ","rn":"Edad No","rk":"EDAD no","rt":"F","g":"M","a":48,"hn":"259","id":null,"pn":261,"dq":0},{"sn":69,"vn":"Muragan","vk":"ಮುರಗನ್‌","rn":"Jagadamba","rk":"ಜಗದಾಂಬ","rt":"F","g":"M","a":38,"hn":"260","id":null,"pn":261,"dq":1},{"sn":70,"vn":"Kevigopal","vk":"ಕೆವಿಗೋಪಾಲ್‌","rn":"Vemkaravashetti","rk":"ವೆಂಕರಾವಶೆಟ್ಟಿ","rt":"F","g":"M","a":54,"hn":"292","id":null,"pn":261,"dq":1},{"sn":71,"vn":"Em Ar","vk":"ಏಮ್‌ ಆರ್‌","rn":"Em Es Ramayya","rk":"ಏಮ್‌ ಏಸ್‌ ರಾಮಯ್ಯ","rt":"F","g":"M","a":68,"hn":"293","id":null,"pn":261,"dq":1},{"sn":72,"vn":"Vivemkatasvami","vk":"ವಿವೆಂಕಟಸ್ವಾಮಿ","rn":"Vemmkataramanaphpa","rk":"ವೆಂಂಕಟರಮಣಫ್ಪ","rt":"F","g":"M","a":56,"hn":"294","id":null,"pn":261,"dq":1},{"sn":73,"vn":"Dinakarrav Ji Vi 308 Biar Gam 45","vk":"ದಿನಕರ್ರಾವ್‌ ಜಿ ವಿ 308 ಬಿಆರ್‌ ಗಂ 45","rn":"","rk":"","rt":"","g":"M","a":45,"hn":"295","id":null,"pn":261,"dq":0},{"sn":74,"vn":"Omkarappa 308 Veerappa Gam 58","vk":"ಒಂಕಾರಪ್ಪ 308 ವೀರಪ್ಪ ಗಂ 58","rn":"","rk":"","rt":"","g":"M","a":58,"hn":"296","id":null,"pn":261,"dq":0},{"sn":75,"vn":"Palviliyamjakuma","vk":"ಪಾಲ್ವಿಲಿಯಂಜಕುಮಾ","rn":"Es Vikebal","rk":"ಏಸ್‌ ವಿಕೇಬಲ್‌","rt":"F","g":"M","a":62,"hn":"297","id":null,"pn":261,"dq":1},{"sn":76,"vn":"Anila Simbal","vk":"ಅನಿಲ ಸಿಂಬಲ್‌","rn":"Amulmallimbal","rk":"ಅಮುಲ್ಮಾಲ್ಲಿಂಬಲ್‌","rt":"F","g":"M","a":64,"hn":"298","id":null,"pn":261,"dq":1},{"sn":77,"vn":"Paphapayyanaydu","vk":"ಪಫಾಪಯ್ಯನಾಯ್ಡು","rn":"Ramacamdrayyana","rk":"ರಾಮಚಂದ್ರಯ್ಯನಾ","rt":"F","g":"M","a":53,"hn":"299","id":null,"pn":261,"dq":1},{"sn":78,"vn":"Kotishcararav","vk":"300... ಕೋಟಿಶ್ಚರರಾವ್‌","rn":"Dashrat Ramayya","rk":"ದಶರತ್‌ ರಾಮಯ್ಯ","rt":"F","g":"M","a":32,"hn":"300...","id":null,"pn":261,"dq":1},{"sn":79,"vn":"2 Alegsamdar","vk":"& 2 ಅಲೆಗ್ಸಾಂಡರ್‌","rn":"Hicako","rk":"ಹಿಚಾಕೊ","rt":"F","g":"M","a":46,"hn":"301","id":null,"pn":261,"dq":1},{"sn":80,"vn":"Hf Ar Sheshadri 308 En Es Raghavan Gam 44","vk":"HF ಅರ್‌ ಶೇಶಾದ್ರಿ 308 ಏನ್‌ ಏಸ್‌ ರಾಘವನ್‌ ಗಂ 44","rn":"","rk":"","rt":"","g":"M","a":44,"hn":"302","id":null,"pn":261,"dq":0},{"sn":81,"vn":"Ar Pratapramarreddi","vk":"ಆರ್‌ ಪ್ರತಾಪ್ರಮಾರ್ರೆಡ್ಡಿ","rn":"Subbaramareddi","rk":"ಸುಬ್ಬರಾಮರೆಡ್ಡಿ","rt":"F","g":"M","a":34,"hn":"303","id":null,"pn":261,"dq":1},{"sn":82,"vn":"Nagapal 308 Karamacammmdanagapa Gam 28","vk":"ನಾಗಪಾಲ್‌ 308 ಕರಮಚಂಂಂದನಾಗಪಾ ಗಂ ೨8","rn":"","rk":"","rt":"","g":"M","a":28,"hn":"304","id":null,"pn":261,"dq":0},{"sn":83,"vn":"Camdrashekhar","vk":"ಚಂದ್ರಶೇಖರ್‌","rn":"Bannappa","rk":"ಬನ್ನಪ್ಪ","rt":"F","g":"M","a":42,"hn":"305","id":null,"pn":261,"dq":1},{"sn":84,"vn":"Alban Sa","vk":"ಆಲ್ಬನ್‌ಸ","rn":"Lulnath","rk":"ಲೂಲ್ನಾಥ್‌","rt":"F","g":"M","a":23,"hn":"306","id":null,"pn":261,"dq":1},{"sn":85,"vn":"En Pamduramga","vk":"ಏನ್‌ ಪಾಂಡುರಂಗ","rn":"Hanumamtappa No 43 -","rk":"ಹನುಮಂತಪ್ಪ no 43 -","rt":"F","g":"M","a":null,"hn":"307","id":null,"pn":261,"dq":1},{"sn":86,"vn":"Jinarayannoti 308 Gururajapoti No 54","vk":"ಜಿನಾರಾಯಣ್ಣೋತಿ 308 ಗುರುರಾಜಪೋತಿ no 54","rn":"","rk":"","rt":"","g":"M","a":null,"hn":"308","id":null,"pn":261,"dq":0},{"sn":87,"vn":"Vishvanath Rav","vk":"ವಿಶ್ವನಾಥ್‌ ರಾವ್‌","rn":"Vemmkatacalapoti","rk":"ವೆಂಂಕಟಚಲಪೋತಿ","rt":"F","g":"M","a":46,"hn":"309","id":null,"pn":261,"dq":1},{"sn":88,"vn":"Dajies Shasti","vk":"ಡಾಜಿಏಸ್‌ ಶಾಸ್ತಿ","rn":"Ji","rk":"ಜಿ","rt":"F","g":"M","a":38,"hn":"311","id":null,"pn":261,"dq":1},{"sn":89,"vn":"Vishivakumar","vk":"ವಿಶಿವಕುಮಾರ್‌","rn":"Vemkatesh Rav","rk":"ವೆಂಕಟೇಶ್‌ ರಾವ್‌","rt":"F","g":"M","a":46,"hn":"312","id":null,"pn":261,"dq":1},{"sn":90,"vn":"Shamkararathod","vk":". ಶಂಕರರಾಥೋಡ್‌","rn":"Roplimg","rk":"ರೋಪ್ಲಿಂಗ್‌","rt":"F","g":"M","a":39,"hn":"343","id":null,"pn":261,"dq":1},{"sn":91,"vn":"Muniratnam","vk":"ಮುನಿರತ್ನಂ","rn":"Munisvami","rk":"ಮುನಿಸ್ವಾಮಿ","rt":"F","g":"M","a":43,"hn":"314","id":null,"pn":261,"dq":1},{"sn":92,"vn":"Ammtonikaus 308 Ponnasvami Gam 46","vk":"ಅಂಂಟೋನಿಕೌಸ್‌ 308 ಪೊನ್ನಸ್ವಾಮಿ ಗಂ 46","rn":"","rk":"","rt":"","g":"M","a":46,"hn":"315","id":null,"pn":261,"dq":0},{"sn":93,"vn":"Eerappa","vk":"ಈರಪ್ಪ","rn":"Vemkataramappa","rk":"ವೆಂಕಟರಾಮಪ್ಪ","rt":"F","g":"M","a":43,"hn":"316","id":null,"pn":261,"dq":1},{"sn":94,"vn":"Devid Kumar","vk":"ಡೇವಿಡ್‌ ಕುಮಾರ್‌","rn":"Munivemkatappa","rk":"ಮುನಿವೆಂಕಟಪ್ಪ","rt":"F","g":"M","a":40,"hn":"317","id":null,"pn":261,"dq":1},{"sn":95,"vn":"Natarajan","vk":"ನಟರಾಜನ್‌","rn":"Ramamurti","rk":", ರಾಮಮೂರ್ತಿ","rt":"F","g":"M","a":23,"hn":"318","id":null,"pn":261,"dq":1},{"sn":96,"vn":"Tivijike Svami","vk":"ಟಿವಿಜಿಕೆ ಸ್ವಾಮಿ","rn":"Lakshmeenarasimha","rk":"ಲಕ್ಷ್ಮೀನರಸಿಂಹ","rt":"F","g":"M","a":59,"hn":"319","id":null,"pn":261,"dq":1},{"sn":97,"vn":"Gurusiddamurti 308 Sicamdrayya Gam 61","vk":"ಗುರುಸಿದ್ದಮೂರ್ತಿ 308 ಸಿಚಂದ್ರಯ್ಯ ಗಂ 61","rn":"","rk":"","rt":"","g":"M","a":61,"hn":"320","id":null,"pn":261,"dq":0},{"sn":98,"vn":"Ar El","vk":"ಆರ್‌ ಏಲ್‌","rn":"Lakshmeenarayanara","rk":"ಲಕ್ಷ್ಮೀನಾರಾಯಣರಾ","rt":"F","g":"M","a":63,"hn":"321","id":null,"pn":261,"dq":1},{"sn":99,"vn":"Em Es Rav","vk":"ಏಂ ಏಸ್‌ ರಾವ್‌","rn":"Em","rk":"ಏಮ್‌","rt":"F","g":"M","a":55,"hn":"322","id":null,"pn":261,"dq":1},{"sn":100,"vn":"Kekishan Camd 308 Krishnanayak Gam 50","vk":"ಕೆಕಿಶನ್‌ ಚಂದ್‌ 308 ಕೃಷ್ಣನಾಯಕ್‌ ಗಂ 50","rn":"","rk":"","rt":"","g":"M","a":50,"hn":"323","id":null,"pn":261,"dq":0},{"sn":101,"vn":"Bharat Prabhu","vk":"ಭರತ್‌ ಪ್ರಭು","rn":"Keshavaraj","rk":"ಕೇಶವರಾಜ್‌","rt":"F","g":"M","a":47,"hn":"324","id":null,"pn":261,"dq":1},{"sn":102,"vn":"Shreenivasanaydnu","vk":"ಶ್ರೀನಿವಾಸನಾಯ್ಡ್ನು","rn":"Abdaynaynu","rk":"ಅಬ್ದಾಯ್ನಾಯ್ನು","rt":"F","g":"M","a":59,"hn":"325","id":null,"pn":261,"dq":1},{"sn":103,"vn":"Thamasaailyak","vk":"ಥಾಮಸಾಐಲ್ಯಕ್‌","rn":"Thamaskalyak","rk":"ಥಾಮಸ್ಕಾಲ್ಯಕ್‌","rt":"F","g":"M","a":45,"hn":"326","id":null,"pn":261,"dq":1},{"sn":104,"vn":"Takhamyuvarajasimg 300 Ar Motisimmg Gam 48","vk":"ಟಖಂಯುವರಾಜಸಿಂಗ್‌ 300 ಆರ್‌ ಮೋತಿಸಿಂಂಗ್‌ ಗಂ 48","rn":"","rk":"","rt":"","g":"M","a":48,"hn":"327","id":null,"pn":261,"dq":0},{"sn":105,"vn":"Vemkatappa","vk":"ವೆಂಕಟಪ್ಪ","rn":"Thimmayya","rk":"ತಿಮ್ಮಯ್ಯ","rt":"F","g":"M","a":53,"hn":"328","id":null,"pn":261,"dq":1},{"sn":106,"vn":"Raman","vk":"ರಾಮನ್‌","rn":"Kumkyyup","rk":"ಕೂಮ್ಕ್ಯ್ಯೂಪ್‌","rt":"F","g":"M","a":61,"hn":"330","id":null,"pn":261,"dq":1},{"sn":107,"vn":"Puttanna","vk":"ಪುಟ್ಟಣ್ಣ","rn":"Mallanna","rk":"ಮಲ್ಲಣ್ಣ","rt":"F","g":"M","a":null,"hn":"332","id":null,"pn":261,"dq":1},{"sn":108,"vn":"Jebasavaraju","vk":"ಜೆಬಸವರಾಜು","rn":"Gamgadarya","rk":"ಗಂಗಾದರ್ಯ","rt":"F","g":"M","a":66,"hn":"333","id":null,"pn":261,"dq":1},{"sn":109,"vn":"Yariktak","vk":"ಯರಿಕ್ಟಾಕ್‌","rn":"Aiddadbak","rk":"ಐಡ್ಡಡ್ಬಾಕ್‌","rt":"F","g":"M","a":60,"hn":"334","id":null,"pn":261,"dq":1},{"sn":110,"vn":"Vemkateshvararaju","vk":"ವೆಂಕಟೇಶ್ವರರಾಜು","rn":"Appalaraju","rk":"ಅಪ್ಪಲಾರಾಜು","rt":"F","g":"M","a":55,"hn":"335","id":null,"pn":261,"dq":1},{"sn":111,"vn":"En Dhanalakshmi","vk":"ಏನ್‌ ಧನಲಕ್ಷ್ಮಿ","rn":"E6Laum Nadam","rk":"ಏ೬್ಳಉಮ್‌ ನಾದಮ್‌","rt":"H","g":"F","a":59,"hn":"336","id":null,"pn":261,"dq":1},{"sn":112,"vn":"Radhabayi","vk":"ರಾಧಬಾಯಿ","rn":"Shreeramuluraju","rk":"ಶ್ರೀರಾಮುಲುರಾಜು","rt":"H","g":"F","a":58,"hn":"337","id":null,"pn":261,"dq":1},{"sn":113,"vn":"Vivakar","vk":"ವಿವಾಕರ್‌","rn":"Paithalmayar","rk":"ಪೈಥಲ್ಮಾಯರ್‌","rt":"F","g":"M","a":48,"hn":"338","id":null,"pn":261,"dq":1},{"sn":114,"vn":"Hareedeepasimg 308 Harbansimg No 63","vk":"ಹರೀದೀಪಸಿಂಗ್‌ 308 ಹರ್ಬನ್ಸಿಂಗ್‌ no 63","rn":"","rk":"","rt":"","g":"M","a":null,"hn":"339","id":null,"pn":261,"dq":0},{"sn":115,"vn":"Padmanababattba","vk":"340... ಪದ್ಮನಾಬಬಟ್ಟ್ಬ","rn":"Gopal Batti","rk":"ಗೋಪಾಲ್‌ ಬಟ್ಟಿ","rt":"F","g":"M","a":37,"hn":"340...","id":null,"pn":261,"dq":1},{"sn":116,"vn":"Ar Es Prasad","vk":"ಆರ್‌ ಏಸ್‌ ಪ್ರಸಾದ್‌","rn":"Pies Sabramanyan","rk":"ಪಿಏಸ್‌ ಸಬ್ರಮಣ್ಯನ್‌","rt":"F","g":"M","a":38,"hn":"341","id":null,"pn":261,"dq":1},{"sn":117,"vn":"Vai En Raju","vk":"ವೈ ಏನ್‌ ರಾಜು","rn":"Namjigauda","rk":"ನಂಜಿಗೌಡ","rt":"F","g":"M","a":51,"hn":"342","id":null,"pn":261,"dq":1},{"sn":118,"vn":"Hitipatel","vk":"ಹಿಟಿಪಟೇಲ್‌","rn":"Ti Es Patel","rk":"ಟಿ ಏಸ್‌ ಪಟೇಲ್‌","rt":"H","g":"F","a":49,"hn":"343","id":null,"pn":261,"dq":1},{"sn":119,"vn":"Keke Somashekharan","vk":"ಕೆಕೆ ಸೋಮಶೇಖರನ್‌","rn":"Sike","rk":"ಸಿಕೆ","rt":"F","g":"M","a":61,"hn":"344","id":null,"pn":261,"dq":1},{"sn":120,"vn":"Tulasidas","vk":"ತುಳಸಿದಾಸ್‌","rn":"Umavati","rk":"ಉಮಾವತಿ","rt":"F","g":"M","a":62,"hn":"345","id":null,"pn":261,"dq":1},{"sn":121,"vn":"Em Subbamanyam","vk":"ಏಂ ಸುಬ್ಬಮಣ್ಯಂ","rn":"Tikemunistami","rk":"ಟಿಕೆಮುನಿಸ್ಟಾಮಿ","rt":"F","g":"M","a":57,"hn":"346","id":null,"pn":261,"dq":1},{"sn":122,"vn":"Pies","vk":"ಪಿಏಸ್‌","rn":"Shivarama","rk":"ಶಿವರಾಮ","rt":"F","g":"M","a":56,"hn":"347","id":null,"pn":261,"dq":1},{"sn":123,"vn":"Rajamani Ar","vk":"ರಾಜಾಮಣಿ ಆರ್‌","rn":"Ramasomi","rk":"ರಾಮಸೋಮಿ","rt":"F","g":"M","a":43,"hn":"348","id":null,"pn":261,"dq":1},{"sn":124,"vn":"Tamdan 308 Etan Tamdan Gam 56","vk":"ತಂಡನ್‌ 308 ಏಟನ್‌ ತಂಡನ್‌ ಗಂ 56","rn":"","rk":"","rt":"","g":"M","a":56,"hn":"349","id":null,"pn":261,"dq":0},{"sn":125,"vn":"Pattabiramu","vk":"350. ಪಟ್ಟಾಬಿರಾಮು","rn":"Ar Ramayya","rk":"ಆರ್‌ ರಾಮಯ್ಯ","rt":"F","g":"M","a":35,"hn":"350.","id":null,"pn":261,"dq":1},{"sn":126,"vn":"Govimdan Aim 308 Es Gam 41","vk":"ಗೋವಿಂದನ್‌ ಐಮ್‌ 308 ಏಸ್‌ ಗಂ 41","rn":"","rk":"","rt":"","g":"M","a":41,"hn":"351","id":null,"pn":261,"dq":0},{"sn":127,"vn":"Timmayya 308 Kempatimmayya Gam 37","vk":"ತಿಮ್ಮಯ್ಯ 308 ಕೆಂಪತಿಮ್ಮಯ್ಯ ಗಂ 37","rn":"","rk":"","rt":"","g":"M","a":37,"hn":"352","id":null,"pn":261,"dq":0},{"sn":128,"vn":"Shreeshaildupad","vk":"ಶ್ರೀಶೈಲ್ದೂಪದ್‌","rn":"Mallayya","rk":"ಮಲ್ಲಯ್ಯ","rt":"F","g":"M","a":39,"hn":"353","id":null,"pn":261,"dq":1},{"sn":129,"vn":"Palraj","vk":"ಪಾಲ್ರಾಜ್‌","rn":"Raju","rk":"ರಾಜು","rt":"F","g":"M","a":47,"hn":"354","id":null,"pn":261,"dq":1},{"sn":130,"vn":"Vijayalakshi","vk":"ವಿಜಯಲಕ್ಷಿ","rn":"Es Ramganathan","rk":"ಏಸ್‌ ರಂಗನಾಥನ್‌","rt":"H","g":"F","a":49,"hn":"355","id":null,"pn":261,"dq":1},{"sn":131,"vn":"En Ar Gopal","vk":"ಏನ್‌ ಆರ್‌ ಗೋಪಾಲ್‌","rn":"Raman","rk":"ರಾಮನ್‌","rt":"F","g":"M","a":58,"hn":"356","id":null,"pn":261,"dq":1},{"sn":132,"vn":"Madhu 308 Krishnappa No 38","vk":"ಮಧು 308 ಕೃಷ್ಣಪ್ಪ no 38","rn":"","rk":"","rt":"","g":"M","a":null,"hn":"357","id":null,"pn":261,"dq":0},{"sn":133,"vn":"Gamgamma","vk":"ಗಂಗಮ್ಮ","rn":"Devappa","rk":"ದೇವಪ್ಪ","rt":"H","g":"M","a":30,"hn":"358","id":null,"pn":261,"dq":0},{"sn":134,"vn":"Virammopal","vk":"ವಿರಾಮ್ಮೋಪಾಲ್‌","rn":"Vemkatesh Prabhu","rk":"ವೆಂಕಟೇಶ್‌ ಪ್ರಭು","rt":"F","g":"M","a":46,"hn":"359","id":null,"pn":261,"dq":1},{"sn":135,"vn":"Jambunathan","vk":"ಜಂಬುನಾಥನ್‌","rn":"Ti Tyagaraj","rk":"ಟಿ ತ್ಯಾಗರಾಜ್‌","rt":"F","g":"M","a":47,"hn":"360","id":null,"pn":261,"dq":1},{"sn":136,"vn":"Ke Vishvanath 308 Kekamanna Gam 38","vk":"ಕೆ ವಿಶ್ವನಾಥ್‌ 308 ಕೆಕಾಮಣ್ಣ ಗಂ 38","rn":"","rk":"","rt":"","g":"M","a":38,"hn":"361","id":null,"pn":261,"dq":0},{"sn":137,"vn":"Kesijagadeesh","vk":"ಕೆಸಿಜಗದೀಶ್‌","rn":"Dh Cikkanna","rk":"DH ಚಿಕ್ಕಣ್ಣ","rt":"F","g":"M","a":58,"hn":"362","id":null,"pn":261,"dq":1},{"sn":138,"vn":"Hec Em","vk":"ಹೆಚ್‌ ಏಂ","rn":"Madavaurala","rk":"ಮಾದವಉರಾಳ","rt":"F","g":"M","a":51,"hn":"363","id":null,"pn":261,"dq":1},{"sn":139,"vn":"Murudavanan","vk":"ಮುರುದವಾನಾನ್‌","rn":"Muragan","rk":"ಮುರಗನ್‌","rt":"F","g":"M","a":68,"hn":"364","id":null,"pn":261,"dq":1},{"sn":140,"vn":"Danatarajan","vk":"ಡಾನಟರಾಜನ್‌","rn":"Annamalai","rk":"ಅಣ್ಣಮಲೈ","rt":"F","g":"M","a":22,"hn":"365","id":null,"pn":261,"dq":1},{"sn":141,"vn":"Mani","vk":"ಮಣಿ","rn":"No 43 -","rk":"no 43 -","rt":"F","g":"M","a":null,"hn":"366","id":null,"pn":261,"dq":1},{"sn":142,"vn":"Subramani","vk":"ಸುಬ್ರಮಣಿ","rn":"Phalaniamdi","rk":"ಫಲನಿಆಂದಿ","rt":"F","g":"M","a":53,"hn":"367","id":null,"pn":261,"dq":1},{"sn":143,"vn":"Hauec Ar Shreeprakash","vk":"ಹೌೆಚ್‌ ಆರ್‌ ಶ್ರೀಪ್ರಕಾಶ್‌","rn":"Hec Es","rk":"ಹೆಚ್‌ ಏಸ್‌","rt":"F","g":"M","a":48,"hn":"368","id":null,"pn":261,"dq":1},{"sn":144,"vn":"Jalajakrappa","vk":"ಜಲಜಾಕ್ರಪ್ಪ","rn":"Dike Kallappa","rk":"ಡಿಕೆ ಕಲ್ಲಪ್ಪ","rt":"F","g":"M","a":37,"hn":"369","id":null,"pn":261,"dq":1},{"sn":145,"vn":"Viar Subramanyalam","vk":"ವಿಆರ್‌ ಸುಬ್ರಮಣ್ಯಲಂ","rn":"Ramganathan","rk":"ರಂಗನಾಥನ್‌","rt":"F","g":"M","a":43,"hn":"370","id":null,"pn":261,"dq":1},{"sn":146,"vn":"Hec Vemkateshaiai 308 Hec Anamtapai Gam 38","vk":"ಹೆಚ್‌ ವೆಂಕಟೇಶೈೈ 308 ಹೆಚ್‌ ಅನಂತಪೈ ಗಂ 38","rn":"","rk":"","rt":"","g":"M","a":38,"hn":"371","id":null,"pn":261,"dq":0},{"sn":147,"vn":"Ar Mohansabu","vk":"ಆರ್‌ ಮೋಹನ್ಸಾಬು","rn":"Bikeramanna","rk":"ಬಿಕೆರಾಮಣ್ಣ","rt":"F","g":"M","a":18,"hn":"4","id":null,"pn":261,"dq":1},{"sn":148,"vn":"Bike Mamjunatha","vk":"ಬಿಕೆ ಮಂಜುನಾಥ","rn":"Ebi Krishnappa","rk":"ಏಬಿ ಕೃಷ್ಣಪ್ಪ","rt":"F","g":"M","a":18,"hn":"15","id":null,"pn":261,"dq":1},{"sn":149,"vn":"Mamata","vk":"ಮಮತಾ","rn":"Visudhakarasvami","rk":"ವಿಸುಧಾಕರಸ್ವಾಮಿ","rt":"H","g":"F","a":19,"hn":"24","id":null,"pn":261,"dq":1},{"sn":150,"vn":"Biem Suresh","vk":"ಬಿಎಂ ಸುರೇಶ್‌","rn":"Ji Munikrishna","rk":"ಜಿ ಮುನಿಕೃಷ್ಣ","rt":"F","g":"M","a":18,"hn":"34","id":null,"pn":261,"dq":1},{"sn":151,"vn":"Es Mahesh","vk":"ಏಸ್‌ ಮಹೇಶ್‌","rn":"Sudhakarasvamivi","rk":"ಸುಧಾಕರಸ್ವಾಮಿವಿ","rt":"F","g":"M","a":18,"hn":"24","id":null,"pn":261,"dq":1},{"sn":152,"vn":"Bike Maheshkumar","vk":"ಬಿಕೆ ಮಹೇಶ್ಕುಮಾರ್‌","rn":"Ebi Krishnappa","rk":"ಏಬಿ ಕೃಷ್ಣಪ್ಪ","rt":"F","g":"M","a":18,"hn":"15","id":null,"pn":261,"dq":1},{"sn":153,"vn":"Ti Shivakumar","vk":"ಟಿ ಶಿವಕುಮಾರ್‌","rn":"Thimmayya","rk":"ತಿಮ್ಮಯ್ಯ","rt":"F","g":"M","a":18,"hn":"4","id":null,"pn":261,"dq":1}]}